pyqs/2023-lab-test/2021A7PS0006P.v
// Name: Yash Sangram Barge
// ID: 2021A7PS0006P

`timescale 1ms/1ns

module JKFF(input J, K, CLK, output reg Q);
	initial Q = 1'b1;

	always @(negedge CLK) begin
		Q <= (J & ~Q) | (~K & Q);
	end
endmodule

module BCD_Counter(output [3:0] Q_out, input CLK);
	JKFF bit0(1'b1, 1'b1, CLK, Q_out[0]);
	
	not q3bar(q3bar, Q_out[3]);
	JKFF bit1(q3bar, 1'b1, Q_out[0], Q_out[1]);
	JKFF bit2(1'b1, 1'b1, Q_out[1], Q_out[2]);
	
	and j3(j3, Q_out[1], Q_out[2]);
	JKFF bit3(j3, 1'b1, Q_out[0], Q_out[3]);
endmodule

module MEM_16(output reg [15:0] D_16, input [3:0] A_4);
	reg [0:15][15:0] mem;
	initial mem = { 16'h0001, 16'h0002, 16'h0004, 16'h0008, 16'h0010, 16'h0020, 16'h0000, 16'h0000,
					16'h0000, 16'h0000, 16'h0400, 16'h0800, 16'h1000, 16'h0000, 16'h0000, 16'h0000 };
	
	always @(A_4)
		D_16 <= mem[A_4];
endmodule

module MUX_16(output O, input [15:0] I_16, input [3:0] S_4);
	assign O = I_16[S_4];
endmodule

module INTG(output OUT, input CLK);
	wire [3:0] Q;
	BCD_Counter counter(Q, CLK);
	
	wire [15:0] D;
	MEM_16 memory(D, Q);
	
	MUX_16 big_mux(OUT, D, Q);
endmodule

module TESTBENCH();
	reg CLK;
	initial CLK = 1'b0;
	always #0.5 CLK = ~CLK;
	
	wire OUT;
	INTG wrapper(OUT, CLK);
	
	initial begin
		$monitor($time, " CLK=%b | OUT=%b", CLK, OUT);
		#23 $finish;
	end
	
	initial begin
		$dumpfile("2021A7PS0006P.vcd");
		$dumpvars;
	end
endmodule

pyqs/2023-lab-test/2021A7PS0006P.vcd
$date
	Thu Dec  7 15:39:51 2023
$end
$version
	Icarus Verilog
$end
$timescale
	1ns
$end
$scope module TESTBENCH $end
$var wire 1 ! OUT $end
$var reg 1 " CLK $end
$scope module wrapper $end
$var wire 1 " CLK $end
$var wire 4 # Q [3:0] $end
$var wire 1 ! OUT $end
$var wire 16 $ D [15:0] $end
$scope module big_mux $end
$var wire 4 % S_4 [3:0] $end
$var wire 1 ! O $end
$var wire 16 & I_16 [15:0] $end
$upscope $end
$scope module counter $end
$var wire 1 " CLK $end
$var wire 1 ' j3 $end
$var wire 1 ( q3bar $end
$var wire 4 ) Q_out [3:0] $end
$scope module bit0 $end
$var wire 1 " CLK $end
$var wire 1 * J $end
$var wire 1 + K $end
$var reg 1 , Q $end
$upscope $end
$scope module bit1 $end
$var wire 1 - CLK $end
$var wire 1 ( J $end
$var wire 1 . K $end
$var reg 1 / Q $end
$upscope $end
$scope module bit2 $end
$var wire 1 0 CLK $end
$var wire 1 1 J $end
$var wire 1 2 K $end
$var reg 1 3 Q $end
$upscope $end
$scope module bit3 $end
$var wire 1 4 CLK $end
$var wire 1 ' J $end
$var wire 1 5 K $end
$var reg 1 6 Q $end
$upscope $end
$upscope $end
$scope module memory $end
$var wire 4 7 A_4 [3:0] $end
$var reg 16 8 D_16 [15:0] $end
$var reg 256 9 mem [255:0] $end
$upscope $end
$upscope $end
$upscope $end
$enddefinitions $end
$comment Show the parameter values. $end
$dumpall
$end
#0
$dumpvars
b1000000000000001000000000000001000000000000001000000000000001000000000000001000000000000000000000000000000000000000000000000000000000000000000000000001000000000000001000000000000001000000000000000000000000000000000000000000000000000000000000 9
b1 8
b0 7
06
15
04
03
12
11
00
0/
1.
0-
0,
1+
1*
b0 )
1(
0'
b1 &
b0 %
b1 $
b0 #
0"
1!
$end
#500000
1"
#1000000
b10 $
b10 &
b10 8
14
1-
1!
b1 #
b1 %
b1 )
b1 7
1,
0"
#1500000
1"
#2000000
10
1/
b100 $
b100 &
b100 8
04
0-
1!
b10 #
b10 %
b10 )
b10 7
0,
0"
#2500000
1"
#3000000
b1000 $
b1000 &
b1000 8
14
1-
1!
b11 #
b11 %
b11 )
b11 7
1,
0"
#3500000
1"
#4000000
13
00
0/
b10000 $
b10000 &
b10000 8
04
0-
1!
b100 #
b100 %
b100 )
b100 7
0,
0"
#4500000
1"
#5000000
b100000 $
b100000 &
b100000 8
14
1-
1!
b101 #
b101 %
b101 )
b101 7
1,
0"
#5500000
1"
#6000000
1'
10
1/
b0 $
b0 &
b0 8
04
0-
0!
b110 #
b110 %
b110 )
b110 7
0,
0"
#6500000
1"
#7000000
14
1-
b111 #
b111 %
b111 )
b111 7
1,
0"
#7500000
1"
#8000000
03
0!
b0 $
b0 &
b0 8
0(
0'
00
16
0/
04
0-
b1000 #
b1000 %
b1000 )
b1000 7
0,
0"
#8500000
1"
#9000000
14
1-
b1001 #
b1001 %
b1001 )
b1001 7
1,
0"
#9500000
1"
#10000000
1!
b1 $
b1 &
b1 8
1(
06
04
0-
b0 #
b0 %
b0 )
b0 7
0,
0"
#10500000
1"
#11000000
b10 $
b10 &
b10 8
14
1-
1!
b1 #
b1 %
b1 )
b1 7
1,
0"
#11500000
1"
#12000000
10
1/
b100 $
b100 &
b100 8
04
0-
1!
b10 #
b10 %
b10 )
b10 7
0,
0"
#12500000
1"
#13000000
b1000 $
b1000 &
b1000 8
14
1-
1!
b11 #
b11 %
b11 )
b11 7
1,
0"
#13500000
1"
#14000000
13
00
0/
b10000 $
b10000 &
b10000 8
04
0-
1!
b100 #
b100 %
b100 )
b100 7
0,
0"
#14500000
1"
#15000000
b100000 $
b100000 &
b100000 8
14
1-
1!
b101 #
b101 %
b101 )
b101 7
1,
0"
#15500000
1"
#16000000
1'
10
1/
b0 $
b0 &
b0 8
04
0-
0!
b110 #
b110 %
b110 )
b110 7
0,
0"
#16500000
1"
#17000000
14
1-
b111 #
b111 %
b111 )
b111 7
1,
0"
#17500000
1"
#18000000
03
0!
b0 $
b0 &
b0 8
0(
0'
00
16
0/
04
0-
b1000 #
b1000 %
b1000 )
b1000 7
0,
0"
#18500000
1"
#19000000
14
1-
b1001 #
b1001 %
b1001 )
b1001 7
1,
0"
#19500000
1"
#20000000
1!
b1 $
b1 &
b1 8
1(
06
04
0-
b0 #
b0 %
b0 )
b0 7
0,
0"
#20500000
1"
#21000000
b10 $
b10 &
b10 8
14
1-
1!
b1 #
b1 %
b1 )
b1 7
1,
0"
#21500000
1"
#22000000
10
1/
b100 $
b100 &
b100 8
04
0-
1!
b10 #
b10 %
b10 )
b10 7
0,
0"
#22500000
1"
#23000000
b1000 $
b1000 &
b1000 8
14
1-
1!
b11 #
b11 %
b11 )
b11 7
1,
0"
